{
  "resourceType": "ClinicalUseDefinition",
  "id": "db01268-clear-cell-renal-carcinoma",
  "type": "indication",
  "subject": [
    {
      "reference": "MedicationKnowledge/db01268"
    }
  ],
  "indication": {
    "diseaseSymptomProcedure": {
      "concept": {
        "text": "clear cell renal carcinoma"
      }
    }
  },
  "extension": [
    {
      "url": "https://setxgnn.yao.care/fhir/StructureDefinition/evidence-level",
      "valueCode": "L5"
    },
    {
      "url": "https://setxgnn.yao.care/fhir/StructureDefinition/txgnn-score",
      "valueDecimal": 0.5
    }
  ]
}